uitestframework/__init__.py
uitestframework/pom.py
uitestframework-0.0.2.dist-info/LICENSE.txt
uitestframework-0.0.2.dist-info/METADATA
uitestframework-0.0.2.dist-info/WHEEL
uitestframework-0.0.2.dist-info/top_level.txt
uitestframework-0.0.2.dist-info/RECORD
