Metadata-Version: 2.1
Name: uitestframework
Version: 0.0.2
Summary: A small package for UI testing in web applications.
Home-page: https://github.com/Joshuacruzc/uitestframework
Author: Joshua Cruz Cintrón
Author-email: joshua.cruz15@upr.edu
License: UNKNOWN
Platform: UNKNOWN
Classifier: Programming Language :: Python :: 3
Classifier: License :: OSI Approved :: MIT License
Classifier: Operating System :: OS Independent
